opcut/ui/script/@hat-open/util/misc.js
opcut/ui/script/snabbdom/build/modules/module.d.ts
opcut/ui/style/_shadow.css
opcut/ui/icons/applications-other.svg
opcut/ui/script/snabbdom/build/modules/dataset.d.ts
opcut/ui/script/snabbdom/build/modules/eventlisteners.js
opcut/ui/script/@hat-open/renderer/README.md
opcut/ui/script/snabbdom/build/is.js
opcut/ui/script/@hat-open/util/timestamp.d.ts
opcut/ui/script/snabbdom/build/index.js.map
opcut/ui/script/snabbdom/build/tovnode.d.ts
opcut/ui/script/snabbdom/build/modules/style.js.map
opcut/ui/icons/README
opcut/ui/script/snabbdom/build/is.d.ts
opcut/ui/script/snabbdom/build/modules/attributes.js
opcut/ui/script/vt/settings.js
opcut/_libopcut.so
opcut/ui/script/snabbdom/build/init.js.map
opcut/ui/script/snabbdom/build/modules/module.js.map
opcut/ui/script/snabbdom/build/init.d.ts
opcut/ui/script/@hat-open/util/index.js
opcut/ui/script/snabbdom/build/tovnode.js.map
opcut/ui/script/snabbdom/build/is.js.map
opcut/ui/script/@hat-open/util/file.d.ts
opcut/ui/script/@hat-open/util/pipe.d.ts
opcut/libopcut.py
opcut/ui/script/snabbdom/build/hooks.d.ts
opcut/ui/script/main.js
opcut/ui/icons/object-rotate-right.svg
opcut/ui/script/@hat-open/util/patch.js
opcut/ui/script/@hat-open/renderer/package.json
opcut/ui/script/@hat-open/util/json.js
opcut/ui/icons/list-add.svg
opcut/generate.py
opcut/ui/script/@hat-open/renderer/index.js
opcut/ui/script/snabbdom/build/helpers/attachto.js
opcut/ui/script/snabbdom/build/modules/eventlisteners.d.ts
opcut/ui/script/@hat-open/util/promise.js
opcut/ui/script/snabbdom/build/h.js.map
opcut/ui/script/snabbdom/build/modules/class.js
opcut/ui/script/@hat-open/util/vnode.d.ts
opcut/__main__.py
opcut/ui/script/snabbdom/build/modules/style.d.ts
opcut/ui/script/snabbdom/build/modules/style.js
opcut/ui/script/@hat-open/util/vnode.js
opcut/ui/script/snabbdom/build/helpers/attachto.d.ts
opcut/ui/script/@hat-open/util/package.json
opcut/ui/script/@hat-open/util/misc.d.ts
opcut/ui/index.html
opcut-0.4.16.dist-info/LICENSE
opcut-0.4.16.dist-info/entry_points.txt
opcut-0.4.16.dist-info/METADATA
opcut-0.4.16.dist-info/WHEEL
opcut-0.4.16.dist-info/RECORD
