Metadata-Version: 2.1
Name: opcut
Version: 0.4.16
Summary: Cutting stock problem optimizer
License: GPLv3
Provides-Extra: dev
Requires-Dist: aiohttp ~=3.10.11
Requires-Dist: hat-aio ~=0.7.12
Requires-Dist: hat-json ~=0.6.2
Requires-Dist: pycairo ~=1.27.0
Requires-Dist: hat-doit ~=0.16.2; extra == 'dev'
Requires-Python: >=3.10
Project-URL: Homepage, https://opcut.kopic.xyz
Project-URL: Repository, https://github.com/bozokopic/opcut.git
